FermaCongress/__init__.py
FermaCongress/annotate.py
FermaCongress/auth.py
FermaCongress/extractferma.py
FermaCongress/formatexcel.py
FermaCongress/planner.py
FermaCongress/postferma.py
FermaCongress/trials.py
fermacongress-1.2.3.dist-info/METADATA
fermacongress-1.2.3.dist-info/WHEEL
fermacongress-1.2.3.dist-info/top_level.txt
fermacongress-1.2.3.dist-info/RECORD
