Metadata-Version: 2.4
Name: FermaCongress
Version: 1.2.3
Summary: A ZoomRx - Ferma Congress package for internal usage
Home-page: https://www.zoomrx.com/ferma/
Author: Ferma Congress Team
Author-email: hema.murapaka@zoomrx.com
License: MIT
Requires-Python: >=3.7
Dynamic: author
Dynamic: author-email
Dynamic: description
Dynamic: description-content-type
Dynamic: home-page
Dynamic: license
Dynamic: requires-python
Dynamic: summary
